[{"email":"luiza@gmail.com","telefone":"12997733444"},{"email":"emailtest@gmail.com","tel":12345678},{},{"email":"luizacintraf@gmail.com","tel":"(12)99272-4354"},{"email":"luizacintraf@gmail.com","tel":"(12)99272-4354"},{"email":"luizacintraf@gmail.com","tel":"(12)99272-4354"},{"email":"luizacintraf@gmail.com","tel":"(12)99272-4354"},{"email":"luizacintraf@gmail.com","tel":"(12)99272-4354"},{"email":"luizacintraf@gmail.com","tel":"(12)99272-4354"},{"email":"luiza@email.com"},{"email":"luiza@email.com"},{"email":"luiza@gmail.com","tel":"(12)99778-2345"}]